MANIFEST.in
README
setup.cfg
setup.py
assets/conf/tangelo.global.conf
assets/conf/tangelo.local.conf
assets/data/get-flickr-data.py
tangelo/__init__.py
tangelo/__main__.py
tangelo/server.py
tangelo/util.py
tangelo/websocket.py
tangelo.egg-info/PKG-INFO
tangelo.egg-info/SOURCES.txt
tangelo.egg-info/dependency_links.txt
tangelo.egg-info/entry_points.txt
tangelo.egg-info/requires.txt
tangelo.egg-info/top_level.txt
tangelo/pkgdata/tangelo.ico
tangelo/pkgdata/plugin/bokeh/requirements.txt
tangelo/pkgdata/plugin/bokeh/python/__init__.py
tangelo/pkgdata/plugin/bokeh/web/bokeh.js
tangelo/pkgdata/plugin/bokeh/web/examples/iris/index.html
tangelo/pkgdata/plugin/bokeh/web/examples/iris/iris.py
tangelo/pkgdata/plugin/config/web/config.js
tangelo/pkgdata/plugin/config/web/config.py
tangelo/pkgdata/plugin/data/web/bin.js
tangelo/pkgdata/plugin/data/web/distanceCluster.js
tangelo/pkgdata/plugin/data/web/smooth.js
tangelo/pkgdata/plugin/data/web/tree.js
tangelo/pkgdata/plugin/docs/web/.buildinfo
tangelo/pkgdata/plugin/docs/web/basic-usage.html
tangelo/pkgdata/plugin/docs/web/bundled-plugins.html
tangelo/pkgdata/plugin/docs/web/coding-style-guide.html
tangelo/pkgdata/plugin/docs/web/developing-visualizations.html
tangelo/pkgdata/plugin/docs/web/genindex.html
tangelo/pkgdata/plugin/docs/web/index.html
tangelo/pkgdata/plugin/docs/web/installation.html
tangelo/pkgdata/plugin/docs/web/objects.inv
tangelo/pkgdata/plugin/docs/web/plugins.html
tangelo/pkgdata/plugin/docs/web/python-services.html
tangelo/pkgdata/plugin/docs/web/releasing-tangelo.html
tangelo/pkgdata/plugin/docs/web/search.html
tangelo/pkgdata/plugin/docs/web/searchindex.js
tangelo/pkgdata/plugin/docs/web/setup.html
tangelo/pkgdata/plugin/docs/web/tangelo-js.html
tangelo/pkgdata/plugin/docs/web/tangelo-manpage.html
tangelo/pkgdata/plugin/docs/web/tangelo-passwd-manpage.html
tangelo/pkgdata/plugin/docs/web/tangelo-py.html
tangelo/pkgdata/plugin/docs/web/.doctrees/basic-usage.doctree
tangelo/pkgdata/plugin/docs/web/.doctrees/bundled-plugins.doctree
tangelo/pkgdata/plugin/docs/web/.doctrees/coding-style-guide.doctree
tangelo/pkgdata/plugin/docs/web/.doctrees/developing-visualizations.doctree
