Metadata-Version: 1.0
Name: tangelo
Version: 0.10.0
Summary: Tangelo Web Framework
Home-page: http://kitware.github.io/tangelo
Author: Kitware, Inc.
Author-email: tangelo-users@public.kitware.com
License: Apache License, Version 2.0
Platform: Linux
Platform: OS X
Platform: Windows
